alphavibe/__init__.py
alphavibe-2.0.1.dist-info/licenses/LICENSE
alphavibe-2.0.1.dist-info/METADATA
alphavibe-2.0.1.dist-info/WHEEL
alphavibe-2.0.1.dist-info/top_level.txt
alphavibe-2.0.1.dist-info/RECORD
