Metadata-Version: 2.4
Name: alphavibe
Version: 2.0.1
Summary: Gen Alpha programming language: Vibe-based Python for Zoomers
Home-page: https://github.com/PotatoInfinity/genalpha-lang
Author: Louis the Sigma
Author-email: developerlouis7923@gmail.com
Classifier: Programming Language :: Python :: 3
Classifier: License :: OSI Approved :: MIT License
Classifier: Operating System :: OS Independent
Classifier: Topic :: Education
Classifier: Topic :: Software Development :: Interpreters
Requires-Python: >=3.6
License-File: LICENSE
Dynamic: author
Dynamic: author-email
Dynamic: classifier
Dynamic: description
Dynamic: description-content-type
Dynamic: home-page
Dynamic: license-file
Dynamic: requires-python
Dynamic: summary
